{"name": "Bird Keeper Aaron", "bg": "grass", "team": [{"current_hp": 70, "status": "", "status_turns": 0, "moves": [{"move": "wingattack", "pp": 35}, {"move": "doubleteam", "pp": 15}, {"move": "endeavor", "pp": 5}, {"move": "whirlwind", "pp": 20}], "held_item": null, "happiness": 70, "ability": "Reckless", "dex_number": "397", "level": 27, "shiny": false, "stats": {"hp": 70, "atk": 47, "def": 37, "spa": 34, "spd": 27, "spe": 59}, "id": null, "name": "Staravia"}, {"current_hp": 73, "status": "", "status_turns": 0, "moves": [{"move": "quickattack", "pp": 30}, {"move": "wingattack", "pp": 35}, {"move": "doubleteam", "pp": 15}, {"move": "endeavor", "pp": 5}], "held_item": null, "happiness": 70, "ability": "Scrappy", "dex_number": "277", "level": 28, "shiny": false, "stats": {"hp": 73, "atk": 59, "def": 42, "spa": 45, "spd": 37, "spe": 77}, "id": null, "name": "Swellow"}, {"current_hp": 82, "status": "", "status_turns": 0, "moves": [{"move": "pursuit", "pp": 20}, {"move": "aerialace", "pp": 20}, {"move": "mirrormove", "pp": 20}, {"move": "agility", "pp": 30}], "held_item": null, "happiness": 70, "ability": "Keen Eye", "dex_number": "022", "level": 29, "shiny": false, "stats": {"hp": 82, "atk": 64, "def": 45, "spa": 39, "spd": 45, "spe": 71}, "id": null, "name": "Fearow"}], "reward": {"base_payout": 32}, "map": "route_15", "sprite": "bird_keeper", "lines": {"lose": "Grounded!"}}